{
  "parent": "minecraft:recipes/root",
  "criteria": {
    "has_pink_sand": {
      "conditions": {
        "items": [
          {
            "items": "biomeswevegone:pink_sand"
          }
        ]
      },
      "trigger": "minecraft:inventory_changed"
    },
    "has_the_recipe": {
      "conditions": {
        "recipe": "biomeswevegone:pink_stained_glass_from_pink_sand"
      },
      "trigger": "minecraft:recipe_unlocked"
    }
  },
  "requirements": [
    [
      "has_the_recipe",
      "has_pink_sand"
    ]
  ],
  "rewards": {
    "recipes": [
      "biomeswevegone:pink_stained_glass_from_pink_sand"
    ]
  }
}