{
  "parent": "biomeswevegone:biomeswevegone/husbandry/root",
  "criteria": {
    "white_puffball_cap": {
      "conditions": {
        "items": [
          {
            "items": [
              "biomeswevegone:white_puffball_cap"
            ]
          }
        ]
      },
      "trigger": "minecraft:inventory_changed"
    }
  },
  "display": {
    "announce_to_chat": true,
    "description": {
      "translate": "advancements.biomeswevegone.husbandry.forager.description"
    },
    "frame": "task",
    "hidden": false,
    "icon": {
      "item": "biomeswevegone:white_puffball_cap"
    },
    "show_toast": true,
    "title": {
      "translate": "advancements.biomeswevegone.husbandry.forager.title"
    }
  },
  "requirements": [
    [
      "white_puffball_cap"
    ]
  ],
  "sends_telemetry_event": true
}